v2log/__init__.py
v2log/analyzer.py
v2log/app.py
v2log/cli.py
v2log/components.py
v2log/utils.py
v2log/data/IP2LOCATION-LITE-DB11.BIN
v2log/utils/__init__.py
v2log/utils/generator.py
v2log/utils/helpers.py
v2log-0.1.2.data/data/example/demo_access.log
v2log-0.1.2.dist-info/METADATA
v2log-0.1.2.dist-info/WHEEL
v2log-0.1.2.dist-info/entry_points.txt
v2log-0.1.2.dist-info/top_level.txt
v2log-0.1.2.dist-info/RECORD
