Metadata-Version: 2.4
Name: v2log
Version: 0.1.2
Summary: A visualization tool for access log analysis
Home-page: https://github.com/s045pd/v2log
Author: s045pd
Author-email: s045pd.x@gmail.com
Classifier: Programming Language :: Python :: 3
Classifier: License :: OSI Approved :: MIT License
Classifier: Operating System :: OS Independent
Requires-Python: >=3.10
Requires-Dist: streamlit>=1.31.0
Requires-Dist: pandas>=2.0.0
Requires-Dist: folium>=0.14.0
Requires-Dist: plotly>=5.18.0
Requires-Dist: IP2Location>=8.10.0
Requires-Dist: numpy>=1.24.0
Requires-Dist: click>=8.0.0
Requires-Dist: streamlit-folium>=0.12.0
Dynamic: author
Dynamic: author-email
Dynamic: classifier
Dynamic: description
Dynamic: description-content-type
Dynamic: home-page
Dynamic: requires-dist
Dynamic: requires-python
Dynamic: summary
